voms_parser/voms_parser.py
voms_parser-0.0.14.dist-info/LICENSE.txt
voms_parser-0.0.14.dist-info/METADATA
voms_parser-0.0.14.dist-info/WHEEL
voms_parser-0.0.14.dist-info/entry_points.txt
voms_parser-0.0.14.dist-info/top_level.txt
voms_parser-0.0.14.dist-info/RECORD
