Metadata-Version: 2.1
Name: voms-parser
Version: 0.0.14
Summary: Dealing with VOMSES lsc etc.
Author: Rob Currie
Author-email: rcurrie@cern.ch
License: WTFPL
Platform: UNKNOWN
License-File: LICENSE.txt
Requires-Dist: argparse
Requires-Dist: pyOpenSSL
Requires-Dist: urllib3
Requires-Dist: xmltodict
